[
  {"code": "A", "name": "A: Anthropogenic"},
  {"code": "C", "name": "C: Colluvial"},
  {"code": "E", "name": "E: Eolian"},
  {"code": "F", "name": "F: Fluvial"},
  {"code": "L", "name": "L: Lacustrine"},
  {"code": "M", "name": "M: Morainal"},
  {"code": "S", "name": "S: Saprolite"},
  {"code": "V", "name": "V: Volcanic"},
  {"code": "W", "name": "W: Marine"},
  {"code": "UU", "name": "UU: Unspecified Unconsolidated"},
  {"code": "R", "name": "R: Bedrock"},
  {"code": "I", "name": "I: Ice"},
  {"code": "B", "name": "B: Bog"},
  {"code": "FE", "name": "FE: Fen"},
  {"code": "SW", "name": "SW: Swamp"},
  {"code": "UO", "name": "UO: Unspecified Organic Genetic Material"}
]
